wagtailmarkdownblock/__init__.py
wagtailmarkdownblock/blocks.py
wagtailmarkdownblock/utils.py
wagtailmarkdownblock/widgets.py
wagtailmarkdownblock/static/plugins/simplemde/simplemde.attach.js
wagtailmarkdownblock/static/plugins/simplemde/simplemde.min.css
wagtailmarkdownblock/static/plugins/simplemde/simplemde.min.js
wagtailmarkdownblock-0.3.3.dist-info/LICENSE
wagtailmarkdownblock-0.3.3.dist-info/METADATA
wagtailmarkdownblock-0.3.3.dist-info/WHEEL
wagtailmarkdownblock-0.3.3.dist-info/top_level.txt
wagtailmarkdownblock-0.3.3.dist-info/RECORD
